[
    { 
        "_id" : "5d1e83c730b18d3a6c108fee", 
        "body_html" : "<ul class=\"tabs\"> \n<li><a href=\"%E2%80%9D#%E2%80%9D\">Notes</a></li>\n \n<li><a href=\"%E2%80%9D#%E2%80%9D\">Details</a></li>\n</ul>\n<ul class=\"tabs-content\"> \n<li>\n<p>Striking, yet lightweight. This pair will be sure to catch anyone's eye with its layered tropical slices.<br> </p>\n</li>\n<li>Acrylic. Imported.</li>\n</ul>", 
        "product_type" : "Jewelry", 
        "title" : "Tortoise Triangle Drop Earrings Tropic", 
        "variants" : [
            {
                "id" : 15429384732762.0, 
                "product_id" : 1572445880410.0, 
                "title" : "Default Title", 
                "price" : "14.50", 
                "sku" : "", 
                "position" : "NumberInt(1)", 
                "inventory_policy" : "deny", 
                "compare_at_price" : "29.00", 
                "fulfillment_service" : "manual", 
                "inventory_management" : "shopify", 
                "option1" : "Default Title", 
                "option2" : null, 
                "option3" : null, 
                "created_at" : "2018-11-21T18:04:50-05:00", 
                "updated_at" : "2019-05-25T14:41:12-04:00", 
                "taxable" : true, 
                "barcode" : "", 
                "grams" : "NumberInt(0)", 
                "image_id" : null, 
                "weight" : "NumberInt(0)", 
                "weight_unit" : "kg", 
                "inventory_item_id" : 15597898727514.0, 
                "inventory_quantity" : "NumberInt(3)", 
                "old_inventory_quantity" : "NumberInt(3)", 
                "requires_shipping" : true, 
                "admin_graphql_api_id" : "gid://shopify/ProductVariant/15429384732762"
            }
        ], 
        "uniqueProductId" : "5c1b1d11e1b8142eeb911b9c-1572445880410"
    },
    { 
        "_id" : "5c73f87f979467674a18c7a8", 
        "title" : "Soia & Kyo Women's Amalie T in Quartz", 
        "body_html" : "AMALIE-T by SOIA &amp; KYO is a beautiful knit hat with a removable fur pom pom. Features a folded knit hem to keep you warm and cable knit detailing to add the finishing touch to your winter attire. An essential and versatile cold-weather accessory<br><br><li>Cable knit with a folded rib knit hem<br>\n</li><li>M'lange yarn for ash only<br>\n</li><li>Removable pom pom (dyed-to-match feather to band colour)<br>\n</li><li>50% wool, 50% acrylic<br>\n</li><li>One Size</li>", 
        "product_type" : "Hats", 
        "variants" : [
            {
                "id" : 18388298268739.0, 
                "product_id" : 1983506546755.0, 
                "title" : "OS", 
                "price" : "65.00", 
                "sku" : "AMALIETOSQRTZSOIKYOCORE", 
                "position" : "NumberInt(1)", 
                "inventory_policy" : "deny", 
                "compare_at_price" : "65.00", 
                "fulfillment_service" : "manual", 
                "inventory_management" : "shopify", 
                "option1" : "OS", 
                "option2" : null, 
                "option3" : null, 
                "created_at" : "2018-12-29T00:44:05-05:00", 
                "updated_at" : "2019-05-10T12:55:32-04:00", 
                "taxable" : true, 
                "barcode" : "677558020196", 
                "grams" : "NumberInt(1000)", 
                "image_id" : 6279244415043.0, 
                "weight" : "NumberInt(1)", 
                "weight_unit" : "kg", 
                "inventory_item_id" : 18653232627779.0, 
                "inventory_quantity" : "NumberInt(7)", 
                "old_inventory_quantity" : "NumberInt(7)", 
                "requires_shipping" : true, 
                "admin_graphql_api_id" : "gid://shopify/ProductVariant/18388298268739"
            }
        ], 
        "uniqueProductId" : "5c61ecb805fc09535fa5b932-1983506546755"
    },
    { 
        "_id" : "5c73f878979467674a18c3c2", 
        "title" : "Liberty Hoops - Mini - Gold", 
        "body_html" : "<meta charset=\"utf-8\"><meta charset=\"utf-8\">\n<p class=\"p1\"><strong>E145</strong></p>\n<meta charset=\"utf-8\"><meta charset=\"utf-8\"><meta charset=\"utf-8\"><meta charset=\"utf-8\"><meta charset=\"utf-8\">\n<p class=\"p1\"><span>A pair of mini flat gold hoops with curves for days!</span></p>\n<p>14k gold plating, hypoallergenic posts<br><span>0.35\"</span><span> width, 0.5\" diameter<br></span><em>Made in Canada</em></p>", 
        "product_type" : "Earrings", 
        "variants" : [
            {
                "id" : 14298452164675.0, 
                "product_id" : 1592210260035.0, 
                "title" : "Default Title", 
                "price" : "75.00", 
                "sku" : "", 
                "position" : "NumberInt(1)", 
                "inventory_policy" : "deny", 
                "compare_at_price" : null, 
                "fulfillment_service" : "manual", 
                "inventory_management" : "shopify", 
                "option1" : "Default Title", 
                "option2" : null, 
                "option3" : null, 
                "created_at" : "2018-09-24T10:33:00-04:00", 
                "updated_at" : "2019-01-18T11:17:38-05:00", 
                "taxable" : true, 
                "barcode" : "", 
                "grams" : "NumberInt(10)", 
                "image_id" : null, 
                "weight" : 0.01, 
                "weight_unit" : "kg", 
                "inventory_item_id" : 14507539791939.0, 
                "inventory_quantity" : "NumberInt(7)", 
                "old_inventory_quantity" : "NumberInt(7)", 
                "requires_shipping" : true, 
                "admin_graphql_api_id" : "gid://shopify/ProductVariant/14298452164675"
            }
        ], 
        "uniqueProductId" : "5c61ecb805fc09535fa5b932-1592210260035"
    },
    { 
        "_id" : "5c73f87c979467674a18c5bf", 
        "title" : "Naturalizer Women's Keiva Softmarble Leather Suede M", 
        "body_html" : "Clean lines add sophisticated style to the sleek Naturalizer Keiva Flat. The cushioned insole, lightweight components, flexible sole and breathable linings deliver the ultimate in comfort that you come to expect from Naturalizer.<br><br><li>True to Size<br>\n</li><li>Heel Height: 3/4\"<br>\n</li><li>Synthetic insole/outsole<br>\n</li><li>Naturalizer N5 Contour<br>\n</li><li>Breathable lining</li>", 
        "product_type" : "Shoes", 
        "variants" : [
            {
                "id" : 18493322592323.0, 
                "product_id" : 1998099185731.0, 
                "title" : "6", 
                "price" : "150.00", 
                "sku" : "736707749453", 
                "position" : "NumberInt(1)", 
                "inventory_policy" : "deny", 
                "compare_at_price" : "150.00", 
                "fulfillment_service" : "manual", 
                "inventory_management" : "shopify", 
                "option1" : "6", 
                "option2" : null, 
                "option3" : null, 
                "created_at" : "2019-01-11T17:05:59-05:00", 
                "updated_at" : "2019-02-22T23:00:29-05:00", 
                "taxable" : true, 
                "barcode" : "736707749453", 
                "grams" : "NumberInt(0)", 
                "image_id" : 6362953580611.0, 
                "weight" : "NumberInt(0)", 
                "weight_unit" : "kg", 
                "inventory_item_id" : 18760185249859.0, 
                "inventory_quantity" : "NumberInt(5)", 
                "old_inventory_quantity" : "NumberInt(5)", 
                "requires_shipping" : true, 
                "admin_graphql_api_id" : "gid://shopify/ProductVariant/18493322592323"
            }, 
            {
                "id" : 18493322625091.0, 
                "product_id" : 1998099185731.0, 
                "title" : "6.5", 
                "price" : "150.00", 
                "sku" : "736707749439", 
                "position" : "NumberInt(2)", 
                "inventory_policy" : "deny", 
                "compare_at_price" : "150.00", 
                "fulfillment_service" : "manual", 
                "inventory_management" : "shopify", 
                "option1" : "6.5", 
                "option2" : null, 
                "option3" : null, 
                "created_at" : "2019-01-11T17:06:00-05:00", 
                "updated_at" : "2019-02-22T23:00:29-05:00", 
                "taxable" : true, 
                "barcode" : "736707749439", 
                "grams" : "NumberInt(0)", 
                "image_id" : 6362953580611.0, 
                "weight" : "NumberInt(0)", 
                "weight_unit" : "kg", 
                "inventory_item_id" : 18760185282627.0, 
                "inventory_quantity" : "NumberInt(5)", 
                "old_inventory_quantity" : "NumberInt(5)", 
                "requires_shipping" : true, 
                "admin_graphql_api_id" : "gid://shopify/ProductVariant/18493322625091"
            }, 
            {
                "id" : 18493322657859.0, 
                "product_id" : 1998099185731.0, 
                "title" : "7", 
                "price" : "150.00", 
                "sku" : "736707749415", 
                "position" : "NumberInt(3)", 
                "inventory_policy" : "deny", 
                "compare_at_price" : "150.00", 
                "fulfillment_service" : "manual", 
                "inventory_management" : "shopify", 
                "option1" : "7", 
                "option2" : null, 
                "option3" : null, 
                "created_at" : "2019-01-11T17:06:00-05:00", 
                "updated_at" : "2019-02-22T23:00:29-05:00", 
                "taxable" : true, 
                "barcode" : "736707749415", 
                "grams" : "NumberInt(0)", 
                "image_id" : 6362953580611.0, 
                "weight" : "NumberInt(0)", 
                "weight_unit" : "kg", 
                "inventory_item_id" : 18760185315395.0, 
                "inventory_quantity" : "NumberInt(5)", 
                "old_inventory_quantity" : "NumberInt(5)", 
                "requires_shipping" : true, 
                "admin_graphql_api_id" : "gid://shopify/ProductVariant/18493322657859"
            }, 
            {
                "id" : 18493322690627.0, 
                "product_id" : 1998099185731.0, 
                "title" : "7.5", 
                "price" : "150.00", 
                "sku" : "736707749385", 
                "position" : "NumberInt(4)", 
                "inventory_policy" : "deny", 
                "compare_at_price" : "150.00", 
                "fulfillment_service" : "manual", 
                "inventory_management" : "shopify", 
                "option1" : "7.5", 
                "option2" : null, 
                "option3" : null, 
                "created_at" : "2019-01-11T17:06:00-05:00", 
                "updated_at" : "2019-02-22T23:00:29-05:00", 
                "taxable" : true, 
                "barcode" : "736707749385", 
                "grams" : "NumberInt(0)", 
                "image_id" : 6362953580611.0, 
                "weight" : "NumberInt(0)", 
                "weight_unit" : "kg", 
                "inventory_item_id" : 18760185348163.0, 
                "inventory_quantity" : "NumberInt(11)", 
                "old_inventory_quantity" : "NumberInt(11)", 
                "requires_shipping" : true, 
                "admin_graphql_api_id" : "gid://shopify/ProductVariant/18493322690627"
            }, 
            {
                "id" : 18493322723395.0, 
                "product_id" : 1998099185731.0, 
                "title" : "8", 
                "price" : "150.00", 
                "sku" : "736707749354", 
                "position" : "NumberInt(5)", 
                "inventory_policy" : "deny", 
                "compare_at_price" : "150.00", 
                "fulfillment_service" : "manual", 
                "inventory_management" : "shopify", 
                "option1" : "8", 
                "option2" : null, 
                "option3" : null, 
                "created_at" : "2019-01-11T17:06:00-05:00", 
                "updated_at" : "2019-02-22T23:00:29-05:00", 
                "taxable" : true, 
                "barcode" : "736707749354", 
                "grams" : "NumberInt(0)", 
                "image_id" : 6362953580611.0, 
                "weight" : "NumberInt(0)", 
                "weight_unit" : "kg", 
                "inventory_item_id" : 18760185380931.0, 
                "inventory_quantity" : "NumberInt(11)", 
                "old_inventory_quantity" : "NumberInt(11)", 
                "requires_shipping" : true, 
                "admin_graphql_api_id" : "gid://shopify/ProductVariant/18493322723395"
            }, 
            {
                "id" : 18493322756163.0, 
                "product_id" : 1998099185731.0, 
                "title" : "8.5", 
                "price" : "150.00", 
                "sku" : "736707749323", 
                "position" : "NumberInt(6)", 
                "inventory_policy" : "deny", 
                "compare_at_price" : "150.00", 
                "fulfillment_service" : "manual", 
                "inventory_management" : "shopify", 
                "option1" : "8.5", 
                "option2" : null, 
                "option3" : null, 
                "created_at" : "2019-01-11T17:06:00-05:00", 
                "updated_at" : "2019-02-22T23:00:29-05:00", 
                "taxable" : true, 
                "barcode" : "736707749323", 
                "grams" : "NumberInt(0)", 
                "image_id" : 6362953580611.0, 
                "weight" : "NumberInt(0)", 
                "weight_unit" : "kg", 
                "inventory_item_id" : 18760185413699.0, 
                "inventory_quantity" : "NumberInt(11)", 
                "old_inventory_quantity" : "NumberInt(11)", 
                "requires_shipping" : true, 
                "admin_graphql_api_id" : "gid://shopify/ProductVariant/18493322756163"
            }, 
            {
                "id" : 18493322788931.0, 
                "product_id" : 1998099185731.0, 
                "title" : "9", 
                "price" : "150.00", 
                "sku" : "736707749293", 
                "position" : "NumberInt(7)", 
                "inventory_policy" : "deny", 
                "compare_at_price" : "150.00", 
                "fulfillment_service" : "manual", 
                "inventory_management" : "shopify", 
                "option1" : "9", 
                "option2" : null, 
                "option3" : null, 
                "created_at" : "2019-01-11T17:06:00-05:00", 
                "updated_at" : "2019-02-22T23:00:29-05:00", 
                "taxable" : true, 
                "barcode" : "736707749293", 
                "grams" : "NumberInt(0)", 
                "image_id" : 6362953580611.0, 
                "weight" : "NumberInt(0)", 
                "weight_unit" : "kg", 
                "inventory_item_id" : 18760185446467.0, 
                "inventory_quantity" : "NumberInt(5)", 
                "old_inventory_quantity" : "NumberInt(5)", 
                "requires_shipping" : true, 
                "admin_graphql_api_id" : "gid://shopify/ProductVariant/18493322788931"
            }, 
            {
                "id" : 18493322821699.0, 
                "product_id" : 1998099185731.0, 
                "title" : "9.5", 
                "price" : "150.00", 
                "sku" : "736707749262", 
                "position" : "NumberInt(8)", 
                "inventory_policy" : "deny", 
                "compare_at_price" : "150.00", 
                "fulfillment_service" : "manual", 
                "inventory_management" : "shopify", 
                "option1" : "9.5", 
                "option2" : null, 
                "option3" : null, 
                "created_at" : "2019-01-11T17:06:00-05:00", 
                "updated_at" : "2019-02-22T23:00:29-05:00", 
                "taxable" : true, 
                "barcode" : "736707749262", 
                "grams" : "NumberInt(0)", 
                "image_id" : 6362953580611.0, 
                "weight" : "NumberInt(0)", 
                "weight_unit" : "kg", 
                "inventory_item_id" : 18760185479235.0, 
                "inventory_quantity" : "NumberInt(5)", 
                "old_inventory_quantity" : "NumberInt(5)", 
                "requires_shipping" : true, 
                "admin_graphql_api_id" : "gid://shopify/ProductVariant/18493322821699"
            }, 
            {
                "id" : 18493322854467.0, 
                "product_id" : 1998099185731.0, 
                "title" : "10", 
                "price" : "150.00", 
                "sku" : "736707749583", 
                "position" : "NumberInt(9)", 
                "inventory_policy" : "deny", 
                "compare_at_price" : "150.00", 
                "fulfillment_service" : "manual", 
                "inventory_management" : "shopify", 
                "option1" : "10", 
                "option2" : null, 
                "option3" : null, 
                "created_at" : "2019-01-11T17:06:00-05:00", 
                "updated_at" : "2019-02-22T23:00:29-05:00", 
                "taxable" : true, 
                "barcode" : "736707749583", 
                "grams" : "NumberInt(0)", 
                "image_id" : 6362953580611.0, 
                "weight" : "NumberInt(0)", 
                "weight_unit" : "kg", 
                "inventory_item_id" : 18760185512003.0, 
                "inventory_quantity" : "NumberInt(5)", 
                "old_inventory_quantity" : "NumberInt(5)", 
                "requires_shipping" : true, 
                "admin_graphql_api_id" : "gid://shopify/ProductVariant/18493322854467"
            }
        ], 
        "uniqueProductId" : "5c61ecb805fc09535fa5b932-1998099185731"
    },
    { 
        "_id" : "5d2fbe0852c5ff03795ea69b", 
        "title" : "Naturalizer Women's Clea Grey M", 
        "body_html" : "This moc front loafer may look innocent; but the edgy heel detail and elongated toe up the style game. Naturalizer Contour Plus addes the comfort features you desire such as a cushioned insole lightweight components flexible sole and breathable linings.<br><br><li>", 
        "product_type" : "Flats", 
        "variants" : [
            {
                "id" : 29425429938243.0, 
                "product_id" : 3933468622915.0, 
                "title" : "6", 
                "price" : "165.00", 
                "sku" : "736712411987", 
                "position" : "NumberInt(1)", 
                "inventory_policy" : "deny", 
                "compare_at_price" : "165.00", 
                "fulfillment_service" : "manual", 
                "inventory_management" : "shopify", 
                "option1" : "6", 
                "option2" : null, 
                "option3" : null, 
                "created_at" : "2019-07-17T20:32:07-04:00", 
                "updated_at" : "2019-07-17T20:32:07-04:00", 
                "taxable" : true, 
                "barcode" : "736712411987", 
                "grams" : "NumberInt(0)", 
                "image_id" : null, 
                "weight" : "NumberInt(0)", 
                "weight_unit" : "lb", 
                "inventory_item_id" : 30543638560835.0, 
                "inventory_quantity" : "NumberInt(0)", 
                "old_inventory_quantity" : "NumberInt(0)", 
                "requires_shipping" : true
            }, 
            {
                "id" : 29425429971011.0, 
                "product_id" : 3933468622915.0, 
                "title" : "6.5", 
                "price" : "165.00", 
                "sku" : "736712411963", 
                "position" : "NumberInt(2)", 
                "inventory_policy" : "deny", 
                "compare_at_price" : "165.00", 
                "fulfillment_service" : "manual", 
                "inventory_management" : "shopify", 
                "option1" : "6.5", 
                "option2" : null, 
                "option3" : null, 
                "created_at" : "2019-07-17T20:32:07-04:00", 
                "updated_at" : "2019-07-17T20:32:07-04:00", 
                "taxable" : true, 
                "barcode" : "736712411963", 
                "grams" : "NumberInt(0)", 
                "image_id" : null, 
                "weight" : "NumberInt(0)", 
                "weight_unit" : "lb", 
                "inventory_item_id" : 30543638593603.0, 
                "inventory_quantity" : "NumberInt(0)", 
                "old_inventory_quantity" : "NumberInt(0)", 
                "requires_shipping" : true
            }, 
            {
                "id" : 29425430003779.0, 
                "product_id" : 3933468622915.0, 
                "title" : "7", 
                "price" : "165.00", 
                "sku" : "736712411949", 
                "position" : "NumberInt(3)", 
                "inventory_policy" : "deny", 
                "compare_at_price" : "165.00", 
                "fulfillment_service" : "manual", 
                "inventory_management" : "shopify", 
                "option1" : "7", 
                "option2" : null, 
                "option3" : null, 
                "created_at" : "2019-07-17T20:32:07-04:00", 
                "updated_at" : "2019-07-17T20:32:07-04:00", 
                "taxable" : true, 
                "barcode" : "736712411949", 
                "grams" : "NumberInt(0)", 
                "image_id" : null, 
                "weight" : "NumberInt(0)", 
                "weight_unit" : "lb", 
                "inventory_item_id" : 30543638626371.0, 
                "inventory_quantity" : "NumberInt(0)", 
                "old_inventory_quantity" : "NumberInt(0)", 
                "requires_shipping" : true
            }, 
            {
                "id" : 29425430036547.0, 
                "product_id" : 3933468622915.0, 
                "title" : "7.5", 
                "price" : "165.00", 
                "sku" : "736712411918", 
                "position" : "NumberInt(4)", 
                "inventory_policy" : "deny", 
                "compare_at_price" : "165.00", 
                "fulfillment_service" : "manual", 
                "inventory_management" : "shopify", 
                "option1" : "7.5", 
                "option2" : null, 
                "option3" : null, 
                "created_at" : "2019-07-17T20:32:07-04:00", 
                "updated_at" : "2019-07-17T20:32:07-04:00", 
                "taxable" : true, 
                "barcode" : "736712411918", 
                "grams" : "NumberInt(0)", 
                "image_id" : null, 
                "weight" : "NumberInt(0)", 
                "weight_unit" : "lb", 
                "inventory_item_id" : 30543638659139.0, 
                "inventory_quantity" : "NumberInt(0)", 
                "old_inventory_quantity" : "NumberInt(0)", 
                "requires_shipping" : true
            }, 
            {
                "id" : 29425430069315.0, 
                "product_id" : 3933468622915.0, 
                "title" : "8", 
                "price" : "165.00", 
                "sku" : "736712411888", 
                "position" : "NumberInt(5)", 
                "inventory_policy" : "deny", 
                "compare_at_price" : "165.00", 
                "fulfillment_service" : "manual", 
                "inventory_management" : "shopify", 
                "option1" : "8", 
                "option2" : null, 
                "option3" : null, 
                "created_at" : "2019-07-17T20:32:07-04:00", 
                "updated_at" : "2019-07-17T20:32:07-04:00", 
                "taxable" : true, 
                "barcode" : "736712411888", 
                "grams" : "NumberInt(0)", 
                "image_id" : null, 
                "weight" : "NumberInt(0)", 
                "weight_unit" : "lb", 
                "inventory_item_id" : 30543638691907.0, 
                "inventory_quantity" : "NumberInt(0)", 
                "old_inventory_quantity" : "NumberInt(0)", 
                "requires_shipping" : true
            }, 
            {
                "id" : 29425430102083.0, 
                "product_id" : 3933468622915.0, 
                "title" : "8.5", 
                "price" : "165.00", 
                "sku" : "736712411857", 
                "position" : "NumberInt(6)", 
                "inventory_policy" : "deny", 
                "compare_at_price" : "165.00", 
                "fulfillment_service" : "manual", 
                "inventory_management" : "shopify", 
                "option1" : "8.5", 
                "option2" : null, 
                "option3" : null, 
                "created_at" : "2019-07-17T20:32:07-04:00", 
                "updated_at" : "2019-07-17T20:32:07-04:00", 
                "taxable" : true, 
                "barcode" : "736712411857", 
                "grams" : "NumberInt(0)", 
                "image_id" : null, 
                "weight" : "NumberInt(0)", 
                "weight_unit" : "lb", 
                "inventory_item_id" : 30543638724675.0, 
                "inventory_quantity" : "NumberInt(0)", 
                "old_inventory_quantity" : "NumberInt(0)", 
                "requires_shipping" : true
            }, 
            {
                "id" : 29425430134851.0, 
                "product_id" : 3933468622915.0, 
                "title" : "9", 
                "price" : "165.00", 
                "sku" : "736712411826", 
                "position" : "NumberInt(7)", 
                "inventory_policy" : "deny", 
                "compare_at_price" : "165.00", 
                "fulfillment_service" : "manual", 
                "inventory_management" : "shopify", 
                "option1" : "9", 
                "option2" : null, 
                "option3" : null, 
                "created_at" : "2019-07-17T20:32:07-04:00", 
                "updated_at" : "2019-07-17T20:32:07-04:00", 
                "taxable" : true, 
                "barcode" : "736712411826", 
                "grams" : "NumberInt(0)", 
                "image_id" : null, 
                "weight" : "NumberInt(0)", 
                "weight_unit" : "lb", 
                "inventory_item_id" : 30543638757443.0, 
                "inventory_quantity" : "NumberInt(0)", 
                "old_inventory_quantity" : "NumberInt(0)", 
                "requires_shipping" : true
            }, 
            {
                "id" : 29425430167619.0, 
                "product_id" : 3933468622915.0, 
                "title" : "10", 
                "price" : "165.00", 
                "sku" : "736712412113", 
                "position" : "NumberInt(8)", 
                "inventory_policy" : "deny", 
                "compare_at_price" : "165.00", 
                "fulfillment_service" : "manual", 
                "inventory_management" : "shopify", 
                "option1" : "10", 
                "option2" : null, 
                "option3" : null, 
                "created_at" : "2019-07-17T20:32:07-04:00", 
                "updated_at" : "2019-07-17T20:32:07-04:00", 
                "taxable" : true, 
                "barcode" : "736712412113", 
                "grams" : "NumberInt(0)", 
                "image_id" : null, 
                "weight" : "NumberInt(0)", 
                "weight_unit" : "lb", 
                "inventory_item_id" : 30543638790211.0, 
                "inventory_quantity" : "NumberInt(0)", 
                "old_inventory_quantity" : "NumberInt(0)", 
                "requires_shipping" : true
            }
        ], 
        "uniqueProductId" : "5c61ecb805fc09535fa5b932-3933468622915"
    },
    { 
        "_id" : "5cc74f1753a9c66327a35c7d", 
        "title" : "Ucon Acrobatics Till Felt Series in Dark Grey", 
        "body_html" : "Can be worn as a backpack or tote, suited for all with out comprimising style. From office to leisure and the commute in between, the Till will keep your belongings close and safe with main compartment zipper.<br><br>\n<li>Phthalate free TPE coating on the inside makes the fabric waterproof and provides additional robustness</li>\n<li>Can be used as a hand bag or backpack</li>\n<li>An internal zip pocket suitable for phone, wallet or passport</li>\n<li>Metal buckle for easy adjustment of shoulder straps</li>\n<li>Cross seam stitching at handle connection</li>", 
        "product_type" : "Bags", 
        "variants" : [
            {
                "id" : 19404263325763.0, 
                "product_id" : 2121979789379.0, 
                "title" : "One Size", 
                "price" : "100.00", 
                "sku" : "699115246618", 
                "position" : "NumberInt(1)", 
                "inventory_policy" : "deny", 
                "compare_at_price" : "100.00", 
                "fulfillment_service" : "manual", 
                "inventory_management" : "shopify", 
                "option1" : "One Size", 
                "option2" : null, 
                "option3" : null, 
                "created_at" : "2019-04-29T15:23:02-04:00", 
                "updated_at" : "2019-05-10T12:30:37-04:00", 
                "taxable" : true, 
                "barcode" : "4260515654518", 
                "grams" : "NumberInt(390000)", 
                "image_id" : 6961140629571.0, 
                "weight" : "NumberInt(390)", 
                "weight_unit" : "kg", 
                "inventory_item_id" : 19693115048003.0, 
                "inventory_quantity" : "NumberInt(1)", 
                "old_inventory_quantity" : "NumberInt(1)", 
                "requires_shipping" : true, 
                "admin_graphql_api_id" : "gid://shopify/ProductVariant/19404263325763"
            }
        ], 
        "uniqueProductId" : "5c61ecb805fc09535fa5b932-2121979789379"
    },
    { 
        "_id" : "5d4045d999dfbd244dec9bef", 
        "title" : "Kodiak Men's Magog Boot in Brown", 
        "body_html" : "Magog is the perfect all-purpose staple boot. Built for all day wear with Thinsulate insulation, a padded comfort collar, and removable leather memory foam insole feet stay comfortable and temperature regulated. The Magog echoes the look of our classic KODIAK work boot with the everyday usability of a hiker style.<br><br><li>Waterproof leather upper<br>\n</li><li>Microfibre lining<br>\n</li><li>Rubber outsole</li>", 
        "product_type" : "Boots", 
        "variants" : [
            {
                "id" : 29477507989571.0, 
                "product_id" : 3942505349187.0, 
                "title" : "8.5", 
                "price" : "225.00", 
                "sku" : "422099DW 85", 
                "position" : "NumberInt(1)", 
                "inventory_policy" : "deny", 
                "compare_at_price" : "225.00", 
                "fulfillment_service" : "manual", 
                "inventory_management" : "shopify", 
                "option1" : "8.5", 
                "option2" : null, 
                "option3" : null, 
                "created_at" : "2019-07-30T09:27:53-04:00", 
                "updated_at" : "2019-07-30T09:27:53-04:00", 
                "taxable" : true, 
                "barcode" : "772259730198", 
                "grams" : "NumberInt(0)", 
                "image_id" : null, 
                "weight" : "NumberInt(0)", 
                "weight_unit" : "lb", 
                "inventory_item_id" : 30614709370947.0, 
                "inventory_quantity" : "NumberInt(0)", 
                "old_inventory_quantity" : "NumberInt(0)", 
                "requires_shipping" : true
            }
        ], 
        "uniqueProductId" : "5c61ecb805fc09535fa5b932-3942505349187"
    },
    { 
        "_id" : "5d3786ba2abe351fc972a7fb", 
        "title" : "Nine West Arch Nemesis Satchel in Cognac Multi", 
        "body_html" : "The Arch Nemesis Satchel has two compartments with a zipper closure on the insid e.  The exterior features adjustable and removable straps with a top handle.<br><br><li>Dimensions: 7 3/4\" H x 10 1/4\" L x 5 1/4\" W<br>\n</li><li>D-ring handle and removable sling strap with 24\" drop<br>\n</li><li>Body Material: 100% PU soft nappa<br>\n</li><li>Shiny brass hardware finish<br>\n</li><li>Interior: 2 slip pockets and 1 zip pocket, magnetic snap closure</li>", 
        "product_type" : "Bags", 
        "variants" : [
            {
                "id" : 29450759929923.0, 
                "product_id" : 3936976830531.0, 
                "title" : "One Size", 
                "price" : "140.00", 
                "sku" : "193314025897", 
                "position" : "NumberInt(1)", 
                "inventory_policy" : "deny", 
                "compare_at_price" : "140.00", 
                "fulfillment_service" : "manual", 
                "inventory_management" : "shopify", 
                "option1" : "One Size", 
                "option2" : null, 
                "option3" : null, 
                "created_at" : "2019-07-23T18:14:17-04:00", 
                "updated_at" : "2019-08-10T01:16:08-04:00", 
                "taxable" : true, 
                "barcode" : "193314025897", 
                "grams" : "NumberInt(1000)", 
                "image_id" : 12020731183171.0, 
                "weight" : "NumberInt(1)", 
                "weight_unit" : "kg", 
                "inventory_item_id" : 30574354530371.0, 
                "inventory_quantity" : "NumberInt(10)", 
                "old_inventory_quantity" : "NumberInt(10)", 
                "requires_shipping" : true, 
                "admin_graphql_api_id" : "gid://shopify/ProductVariant/29450759929923"
            }
        ], 
        "uniqueProductId" : "5c61ecb805fc09535fa5b932-3936976830531"
    },
    { 
        "_id" : "5d1e83c330b18d3a6c108a26", 
        "body_html" : "<ul class=\"tabs\">\n<li><a href=\"%E2%80%9D#%E2%80%9D\">Notes</a></li>\n<li><a href=\"%E2%80%9D#%E2%80%9D\">Details</a></li>\n</ul>\n<ul class=\"tabs-content\">\n<li>This grey with a hint of purple undertone is a great neutral colour to wear. American made and cruelty and vegan free.</li>\n<li>\n<p>Made in the USA, Vegan, Cruelty free, Dibutyl Phthalate, Formaldehyde, Toluene, Formaldehyde Resin, and Camphor free <br><br></p>\n</li>\n</ul>", 
        "product_type" : "Apothecary", 
        "title" : "Misa Nail Polish Deep Breath", 
        "variants" : [
            {
                "id" : 28848258753.0, 
                "product_id" : 8547999361.0, 
                "title" : "Default Title", 
                "price" : "4.00", 
                "sku" : "", 
                "position" : "NumberInt(1)", 
                "inventory_policy" : "deny", 
                "compare_at_price" : "8.00", 
                "fulfillment_service" : "manual", 
                "inventory_management" : "shopify", 
                "option1" : "Default Title", 
                "option2" : null, 
                "option3" : null, 
                "created_at" : "2016-12-15T15:59:43-05:00", 
                "updated_at" : "2019-05-25T14:34:57-04:00", 
                "taxable" : true, 
                "barcode" : "", 
                "grams" : "NumberInt(0)", 
                "image_id" : null, 
                "weight" : "NumberInt(0)", 
                "weight_unit" : "kg", 
                "inventory_item_id" : 16360870465.0, 
                "inventory_quantity" : "NumberInt(1)", 
                "old_inventory_quantity" : "NumberInt(1)", 
                "requires_shipping" : true, 
                "admin_graphql_api_id" : "gid://shopify/ProductVariant/28848258753"
            }
        ], 
        "uniqueProductId" : "5c1b1d11e1b8142eeb911b9c-8547999361"
    },
    { 
        "_id" : "5d011110dcaadc4172dcd575", 
        "title" : "Kodiak Men's Magog Boot in Brown", 
        "body_html" : "Magog is the perfect all-purpose staple boot. Built for all day wear with Thinsulate insulation, a padded comfort collar, and removable leather memory foam insole feet stay comfortable and temperature regulated. The Magog echoes the look of our classic KODIAK work boot with the everyday usability of a hiker style.<br><br><li>Waterproof leather upper<br>\n</li><li>Microfibre lining<br>\n</li><li>Rubber outsole</li>", 
        "product_type" : "Boots", 
        "variants" : [
            {
                "id" : 29061455151171.0, 
                "product_id" : 3826271486019.0, 
                "title" : "8.5", 
                "price" : "225.00", 
                "sku" : "422099DW 85", 
                "position" : "NumberInt(1)", 
                "inventory_policy" : "deny", 
                "compare_at_price" : "225.00", 
                "fulfillment_service" : "manual", 
                "inventory_management" : "shopify", 
                "option1" : "8.5", 
                "option2" : null, 
                "option3" : null, 
                "created_at" : "2019-06-12T10:49:51-04:00", 
                "updated_at" : "2019-06-12T10:49:51-04:00", 
                "taxable" : true, 
                "barcode" : "772259730198", 
                "grams" : "NumberInt(0)", 
                "image_id" : null, 
                "weight" : "NumberInt(0)", 
                "weight_unit" : "lb", 
                "inventory_item_id" : 30113173176387.0, 
                "inventory_quantity" : "NumberInt(0)", 
                "old_inventory_quantity" : "NumberInt(0)", 
                "requires_shipping" : true
            }
        ], 
        "uniqueProductId" : "5c61ecb805fc09535fa5b932-3826271486019"
    }
]